a2a_session_manager/__init__.py
a2a_session_manager/exceptions.py
a2a_session_manager/infinite_conversation.py
a2a_session_manager/session_aware_tool_processor.py
a2a_session_manager/session_prompt_builder.py
a2a_session_manager/models/__init__.py
a2a_session_manager/models/event_source.py
a2a_session_manager/models/event_type.py
a2a_session_manager/models/session.py
a2a_session_manager/models/session_event.py
a2a_session_manager/models/session_metadata.py
a2a_session_manager/models/session_run.py
a2a_session_manager/models/token_usage.py
a2a_session_manager/storage/__init__.py
a2a_session_manager/storage/base.py
a2a_session_manager/storage/providers/__init__.py
a2a_session_manager/storage/providers/file.py
a2a_session_manager/storage/providers/memory.py
a2a_session_manager/storage/providers/redis.py
a2a_session_manager-0.1.3.dist-info/licenses/LICENSE.MD
a2a_session_manager-0.1.3.dist-info/METADATA
a2a_session_manager-0.1.3.dist-info/WHEEL
a2a_session_manager-0.1.3.dist-info/top_level.txt
a2a_session_manager-0.1.3.dist-info/RECORD
