Metadata-Version: 2.4
Name: a2a-session-manager
Version: 0.1.3
Summary: Session manager for A2A applications
Requires-Python: >=3.11
License-File: LICENSE.MD
Requires-Dist: pydantic>=2.11.3
Provides-Extra: tiktoken
Requires-Dist: tiktoken>=0.9.0; extra == "tiktoken"
Provides-Extra: tool-processor
Requires-Dist: chuk-tool-processor>=0.1.2; extra == "tool-processor"
Provides-Extra: redis
Requires-Dist: redis>=4.0.0; extra == "redis"
Provides-Extra: dev
Requires-Dist: pytest>=7.0.0; extra == "dev"
Requires-Dist: pytest-cov>=4.0.0; extra == "dev"
Requires-Dist: redis>=4.0.0; extra == "dev"
Requires-Dist: black>=23.0.0; extra == "dev"
Requires-Dist: isort>=5.12.0; extra == "dev"
Requires-Dist: mypy>=1.0.0; extra == "dev"
Provides-Extra: full
Dynamic: license-file
